iamxed/__init__.py
iamxed/iamxed.py
iamxed/io_utils.py
iamxed/physics.py
iamxed/plotting.py
iamxed/ESF/esf_data.py
iamxed/ESF/example_elsepa_c.in
iamxed/XSF/Szaloki_params_inelastic.csv
iamxed/XSF/inealstic_source
iamxed/XSF/xsf_data_elastic.py
iamxed-1.1.0.dist-info/METADATA
iamxed-1.1.0.dist-info/WHEEL
iamxed-1.1.0.dist-info/entry_points.txt
iamxed-1.1.0.dist-info/licenses/LICENSE
iamxed-1.1.0.dist-info/RECORD
