Metadata-Version: 2.4
Name: iamxed
Version: 1.1.0
Summary: Independent Atom Model for X-ray and Electron Diffraction (XED) Calculator
Project-URL: Homepage, https://github.com/blevine37/IAM-XED
Project-URL: Documentation, https://github.com/blevine37/IAM-XED/blob/main/README.md
Project-URL: Repository, https://github.com/blevine37/IAM-XED.git
Project-URL: Issues, https://github.com/blevine37/IAM-XED/issues
Author-email: Jiri Suchan <suchanjiri@yahoo.com>, Jiri Janos <jiri.janos98@gmail.com>
License: MIT License
License-File: LICENSE
Classifier: Development Status :: 5 - Production/Stable
Classifier: License :: OSI Approved :: MIT License
Classifier: Programming Language :: Python
Classifier: Programming Language :: Python :: 3 :: Only
Classifier: Topic :: Scientific/Engineering
Requires-Python: >=3.9
Requires-Dist: matplotlib>=3.9.0
Requires-Dist: numpy>=1.20
Requires-Dist: scipy>=1.7.0
Requires-Dist: tqdm>=4.50.0
Provides-Extra: test
Requires-Dist: pytest>=7.4; extra == 'test'
